shapeandshare/dicebox/__init__.py
shapeandshare/dicebox/primordialpool.py
shapeandshare/dicebox/config/base_config.py
shapeandshare/dicebox/config/dicebox_config.py
shapeandshare/dicebox/connectors/filesystem_connector.py
shapeandshare/dicebox/connectors/sensory_service_connector.py
shapeandshare/dicebox/factories/layer_factory.py
shapeandshare/dicebox/factories/network_factory.py
shapeandshare/dicebox/models/dicebox_network.py
shapeandshare/dicebox/models/layer.py
shapeandshare/dicebox/models/network.py
shapeandshare/dicebox/models/optimizers.py
shapeandshare/dicebox/optimizers/evolutionary_optimizer.py
shapeandshare/dicebox/utils/helpers.py
shapeandshare_dicebox_core-3.5.0.dist-info/LICENSE.txt
shapeandshare_dicebox_core-3.5.0.dist-info/METADATA
shapeandshare_dicebox_core-3.5.0.dist-info/WHEEL
shapeandshare_dicebox_core-3.5.0.dist-info/top_level.txt
shapeandshare_dicebox_core-3.5.0.dist-info/RECORD
