Metadata-Version: 2.1
Name: shapeandshare-dicebox-core
Version: 3.5.0
Summary: Dicebox Core
Home-page: https://github.com/shapeandshare/dicebox.core
Author: Joshua C. Burt
Author-email: joshburt@shapeandshare.com
License: UNKNOWN
Platform: UNKNOWN
Classifier: Intended Audience :: Developers
Classifier: License :: OSI Approved :: MIT License
Classifier: Programming Language :: Python :: 3.7
Classifier: Programming Language :: Python :: 3.8
Requires-Python: >=3.7
Requires-Dist: numpy (==1.19.2)
Requires-Dist: tensorflow (==2.4.0)
Requires-Dist: pillow (==8.1.0)
Requires-Dist: configparser (==5.0.1)
Requires-Dist: pika (==1.1.0)
Requires-Dist: requests (==2.25.1)
Requires-Dist: typing (==3.7.4.3)
Requires-Dist: tqdm (==4.55.1)
Requires-Dist: uuid (==1.30)
